[
  {
    "content": "News is Working!",
    "url": "#"
  }, {
    "content": "News is still Working!",
    "url": "#"
  }, {
    "content": "News is Still Still  Still Still Still Still Still Still Still Still Still Still Still Still Still Still Still Still Still Still Still Still Still Still Still Still Still Still Still Still Still Still Working!",
    "url": "#"
  }, {
    "content": "Everything is  Still Working!",
    "url": "#"
  }, {
    "content": "Everything is  Still Working!",
    "url": "#"
  }, {
    "content": "Everything is  Still Working!",
    "url": "#"
  }, {
    "content": "Everything is  Still Working!",
    "url": "#"
  }, {
    "content": "Everything is  Still Working!",
    "url": "#"
  }, {
    "content": "Everything is  Still Working!",
    "url": "#"
  }, {
    "content": "Everything is  Still Working!",
    "url": "#"
  }, {
    "content": "Everything is  Still Working!",
    "url": "#"
  }, {
    "content": "Everything is  Still Working!",
    "url": "#"
  }, {
    "content": "Everything is  Still Working!",
    "url": "#"
  }, {
    "content": "Everything is  Still Working!",
    "url": "#"
  }, {
    "content": "Everything is  Still Working!",
    "url": "#"
  }
]
